intl_tel_input/__init__.py
intl_tel_input/widgets.py
intl_tel_input/static/intl_tel_input/init.js
testapp/__init__.py
testapp/forms.py
testapp/manage.py
testapp/settings.py
testapp/tests.py
testapp/urls.py
testapp/views.py
testapp/wsgi.py
django_intl_tel_input-0.4.0.dist-info/LICENSE
django_intl_tel_input-0.4.0.dist-info/METADATA
django_intl_tel_input-0.4.0.dist-info/WHEEL
django_intl_tel_input-0.4.0.dist-info/top_level.txt
django_intl_tel_input-0.4.0.dist-info/RECORD
